SidraApiPythonClient/__init__.py
SidraApiPythonClient/api_client.py
SidraApiPythonClient/authentication.py
SidraApiPythonClient/configuration.py
SidraApiPythonClient/rest.py
SidraApiPythonClient/api/__init__.py
SidraApiPythonClient/api/apps_registry/__init__.py
SidraApiPythonClient/api/apps_registry/app_api.py
SidraApiPythonClient/api/apps_registry/identity_server_users_api.py
SidraApiPythonClient/api/assets/__init__.py
SidraApiPythonClient/api/assets/assets_api.py
SidraApiPythonClient/api/data_factory/__init__.py
SidraApiPythonClient/api/data_factory/activity_templates/__init__.py
SidraApiPythonClient/api/data_factory/activity_templates/activity_templates_api.py
SidraApiPythonClient/api/data_factory/data_factories/__init__.py
SidraApiPythonClient/api/data_factory/data_factories/data_factories_api.py
SidraApiPythonClient/api/data_factory/data_set_template_pipeline_templates/__init__.py
SidraApiPythonClient/api/data_factory/data_set_template_pipeline_templates/data_set_template_pipeline_template_api.py
SidraApiPythonClient/api/data_factory/data_set_templates/__init__.py
SidraApiPythonClient/api/data_factory/data_set_templates/data_set_templates_api.py
SidraApiPythonClient/api/data_factory/data_source_template_pipeline_templates/__init__.py
SidraApiPythonClient/api/data_factory/data_source_template_pipeline_templates/data_source_template_pipeline_template_api.py
SidraApiPythonClient/api/data_factory/data_source_templates/__init__.py
SidraApiPythonClient/api/data_factory/data_source_templates/data_source_template_api.py
SidraApiPythonClient/api/data_factory/data_sources/__init__.py
SidraApiPythonClient/api/data_factory/data_sources/data_source_api.py
SidraApiPythonClient/api/data_factory/pipeline_templates/__init__.py
SidraApiPythonClient/api/data_factory/pipeline_templates/pipeline_templates_api.py
SidraApiPythonClient/api/data_factory/pipelines/__init__.py
SidraApiPythonClient/api/data_factory/pipelines/pipelines_api.py
SidraApiPythonClient-1.13.0.dist-info/LICENSE
SidraApiPythonClient-1.13.0.dist-info/METADATA
SidraApiPythonClient-1.13.0.dist-info/WHEEL
SidraApiPythonClient-1.13.0.dist-info/top_level.txt
SidraApiPythonClient-1.13.0.dist-info/RECORD
