Metadata-Version: 2.1
Name: SidraApiPythonClient
Version: 1.13.0
Summary: A wrapper client for SIDRA API
Home-page: https://sidra.dev/
Author: Sidra Data Services
License: Copyright (c) 2023 Sidra Data Services
License-File: LICENSE
